uart.v
//
// uart.v - for the PDP-8 in Verilog project
//
// github.com/SmallRoomLabs/PDP8-Verilog
// Mats Engstrom - mats.engstrom@gmail.com
//
`default_nettype none

module uart (
  input SYSCLK,
  input RESET,
  input [7:0] txData, // data to be transmitted serially onto tx
  input txStb,        // positive going strobe for the txData - 1 SYSCLK
  output tx,          // serial output stream in 8N1 format with high idle
  output txRdy,       // high when the uart is ready to accept new data
  input rx,
  output [7:0] rxData,
  input rxAck,
  output rxRdy
);

//
// ....----------+       +     +     +     +     +     +     +     +     +      +----------....
//          idle | start | lsb | bit | bit | bit | bit | bit | bit | msb | stop | idle
//               +-------+     +     +     +     +     +     +     +     +------+
//

parameter XTAL              = 100_000_000;
// parameter BAUD           = 6_250_000;  // 60
// parameter BAUD           = 3686400;    // 62
// parameter BAUD           = 1843200;    // 65
// parameter BAUD           = 921600;     // 66
// parameter BAUD           = 460800;     // 68
// parameter BAUD           = 230400;     // 69
parameter BAUD           = 115200;     // 70
// parameter BAUD           = 76800;      // 72
// parameter BAUD           = 19200;      // 74
// parameter BAUD           = 9600;       // 76
// parameter BAUD           = 4800;       // 77
// parameter BAUD           = 2400;       // 78
// parameter BAUD           = 1200;       // 80
// parameter BAUD           = 600;        // 81
// parameter BAUD           = 300;        // 82
// parameter BAUD           = 150;        // 84
// parameter BAUD           = 110;        // 84
// parameter BAUD           = 75;         // 85
parameter BAUDDIVIDER8X     = XTAL/(BAUD*8);
parameter BAUDDIVIDER_WIDTH = $clog2(BAUDDIVIDER8X);

//
// ▁ ▂ ▄ ▅ ▆ ▇ █ BAUDRATE DIVIDER █ ▇ ▆ ▅ ▄ ▂ ▁
//

// Divide the SYSCLK down to the 8x baud rate as well as the real baudrate.
// The 8x baud is used to time the midpoint of the samples in the RX handling.

reg [BAUDDIVIDER_WIDTH-1:0] baud8x=0; 
reg baudTick8x=0;
reg [2:0] baudCnt=0;  // Counter to divide the 8xbaud clock to the real baudrate
reg baudTick=0;       // Strobes at baudrate speed - 1 SYSCLK

always @(posedge SYSCLK) begin
  if (RESET) begin
  end
end

always @(posedge SYSCLK) begin
  baud8x <= baud8x + 1;
  if ({32'b0,baud8x}==BAUDDIVIDER8X-1) begin 
    baud8x <= 0;
    baudTick8x <= 1;
  end 
  if (baudTick8x) begin 
    baudTick8x <= 0;
    baudCnt<=baudCnt+1;
    if (baudCnt==0) baudTick<=1;
  end
  if (baudTick) baudTick <= 0;
end

//
// ▁ ▂ ▄ ▅ ▆ ▇ █ UART RECEIVE █ ▇ ▆ ▅ ▄ ▂ ▁
//

//
//
//

reg [3:0] rxCnt=0;
reg [8:0] rxBuf=0;
reg [3:0] nextMiddle=0;
reg rxReady=0;
reg ping=0;

always @(posedge SYSCLK) begin
  if (rxAck) rxReady<=0;
  if (baudTick8x) begin
    if (rxCnt==0) begin
      if (~rx) begin
        // Detected the startbit
        nextMiddle <= 10;
        rxCnt <= rxCnt + 1;
        rxBuf <= 0;
        ping<=1;
        rxReady <= 0;
      end
    end else if (nextMiddle!=0) begin
      nextMiddle <= nextMiddle-1;
    end else begin
      ping<=1;
      rxBuf <= rxBuf >> 1;
      rxBuf[8] <= rx;
      rxCnt <= rxCnt+1;
      nextMiddle <= 7;
      if (rxCnt>8) begin
        rxCnt <= 0;
        rxReady <= 1;
      end

    end
  end
  if (ping) ping<=0;
end

assign rxData = rxBuf[7:0];
assign rxRdy = rxReady;

//
// ▁ ▂ ▄ ▅ ▆ ▇ █ UART TRANSMIT █ ▇ ▆ ▅ ▄ ▂ ▁
//

//
//
//

reg [9:0] txBuf=0;    // The byte being transmitted plus Start and Stop bits
reg [3:0] txCnt=0;    // Counter for the bits of the byte while transmitting
reg txTriggered=0;    // Set high at txStb and low when the transmission starts
                      // at the next baudTick
always @(posedge SYSCLK) begin
  if (txStb) begin
    // At TX strobe store the new data and set the triggered flag to start
    // waiting for the next baudTick
    txBuf <= {1'b0, ~txData, 1'b1};
    txTriggered <= 1;
  end else if (txTriggered & baudTick) begin
    // It's time to start sending the pending data
    txTriggered <= 0;
    txCnt <= 9;
  end else if (txCnt!=0 & baudTick) begin
    // As long as not all bits are sent - output the next bit
    txBuf <= txBuf / 2;
    txCnt <= txCnt - 1;
  end
end

//
// The TX output stream needs to be inverted since it's stored invered to have the
// remaining (after all bits are sent) zero-value in the register to be outputted as 'one'
// representing the idle state. 
//
// The oring of the txTrigger keeps the TX as idle until the actual sending starts at the
// next baudTick.
//
assign tx=~txBuf[0] | txTriggered;

//
// The ready signal is set already in the stop bit so it can be possible to send data
// back-to-back.  Even is the controller strobes in new data in the middle of the stopbit
// the new transmission will not start unti the next baudTick.
//
// By anding the txTrigger the ready bit will be deactivated as soon as the txStb arrives
//
assign txRdy=(txCnt==0) & ~txTriggered;

endmodule

uart.vt
`timescale 100ns/10ns

module uart_tb();
    reg SYSCLK=0;
    reg RESET=0;
    reg [7:0] txData=0;
    reg txStb=0;
    wire tx;
    wire txRdy;
//    reg rx=1;
    wire rxRdy;
    reg rxAck=0;

    uart dut(
        .SYSCLK(SYSCLK),
        .RESET(RESET),
        .txData(txData),
        .txStb(txStb),
        .tx(tx),
        .txRdy(txRdy),
        .rx(rx),
        .rxRdy(rxRdy),
        .rxAck(rxAck)
    );
    
    initial begin 
        RESET<=1; #5 RESET<=0; 
        $dumpfile("uart.vcd");
        $dumpvars(0,uart_tb);
        #100000 $finish;
    end  

    always begin
        #1 SYSCLK<=~SYSCLK;
    end

    always @(posedge SYSCLK) begin
      if (rxRdy & ~rxAck) begin
        $display("Received %02x",dut.rxData);
        rxAck<=1;
      end
      if (rxAck) rxAck<=0;
    end

    // always begin
    //   #1000; // Idle
    //   #16 rx<=0;  // Start 
    //   #16 rx<=1; #16 rx<=0; #16 rx<=1; #16 rx<=0; #16 rx<=1; #16 rx<=0; #16 rx<=1; #16 rx<=0;
    //   #16 rx<=1; // Stop

    //   #300; // Idle
    //   #16 rx<=0;  // Start 
    //   #16 rx<=0; #16 rx<=0; #16 rx<=0; #16 rx<=0; #16 rx<=0; #16 rx<=0; #16 rx<=0; #16 rx<=0;
    //   #16 rx<=1; // Stop


    //   #300; // Idle
    //   #16 rx<=0;  // Start 
    //   #16 rx<=1; #16 rx<=0; #16 rx<=0; #16 rx<=0; #16 rx<=0; #16 rx<=0; #16 rx<=0; #16 rx<=0;
    //   #16 rx<=1; // Stop

    //   #300; // Idle
    //   #16 rx<=0;  // Start 
    //   #16 rx<=1; #16 rx<=1; #16 rx<=0; #16 rx<=0; #16 rx<=0; #16 rx<=0; #16 rx<=0; #16 rx<=0;
    //   #16 rx<=1; // Stop

    //   #300; // Idle
    //   #16 rx<=0;  // Start 
    //   #16 rx<=1; #16 rx<=1; #16 rx<=1; #16 rx<=0; #16 rx<=0; #16 rx<=0; #16 rx<=0; #16 rx<=0;
    //   #16 rx<=1; // Stop

    //   #300; // Idle
    //   #16 rx<=0;  // Start 
    //   #16 rx<=1; #16 rx<=1; #16 rx<=1; #16 rx<=1; #16 rx<=0; #16 rx<=0; #16 rx<=0; #16 rx<=0;
    //   #16 rx<=1; // Stop

    //   #300; // Idle
    //   #16 rx<=0;  // Start 
    //   #16 rx<=1; #16 rx<=1; #16 rx<=1; #16 rx<=1; #16 rx<=1; #16 rx<=0; #16 rx<=0; #16 rx<=0;
    //   #16 rx<=1; // Stop

    //   #300; // Idle
    //   #16 rx<=0;  // Start 
    //   #16 rx<=1; #16 rx<=1; #16 rx<=1; #16 rx<=1; #16 rx<=1; #16 rx<=1; #16 rx<=0; #16 rx<=0;
    //   #16 rx<=1; // Stop

    //   #300; // Idle
    //   #16 rx<=0;  // Start 
    //   #16 rx<=1; #16 rx<=1; #16 rx<=1; #16 rx<=1; #16 rx<=1; #16 rx<=1; #16 rx<=1; #16 rx<=0;
    //   #16 rx<=1; // Stop

    //   #300; // Idle
    //   #16 rx<=0;  // Start 
    //   #16 rx<=1; #16 rx<=1; #16 rx<=1; #16 rx<=1; #16 rx<=1; #16 rx<=1; #16 rx<=1; #16 rx<=1;
    //   #16 rx<=1; // Stop

    //   #200000; // Idle
    // end

    assign rx=tx;

    reg [7:0]v=8'h55;
    always begin
        #20000; 
        txData<=v; txStb<=1; #2; txStb<=0;
        v<=v+1;
    end
    

endmodule

uart.vcd
$date
	Thu Feb  6 10:26:10 2020
$end
$version
	Icarus Verilog
$end
$timescale
	10ns
$end
$scope module uart_tb $end
$var wire 1 ! rx $end
$var wire 1 " txRdy $end
$var wire 1 # tx $end
$var wire 1 $ rxRdy $end
$var reg 1 % RESET $end
$var reg 1 & SYSCLK $end
$var reg 1 ' rxAck $end
$var reg 8 ( txData [7:0] $end
$var reg 1 ) txStb $end
$var reg 8 * v [7:0] $end
$scope module dut $end
$var wire 1 % RESET $end
$var wire 1 & SYSCLK $end
$var wire 1 ! rx $end
$var wire 1 ' rxAck $end
$var wire 1 $ rxRdy $end
$var wire 1 # tx $end
$var wire 8 + txData [7:0] $end
$var wire 1 " txRdy $end
$var wire 1 ) txStb $end
$var wire 8 , rxData [7:0] $end
$var reg 7 - baud8x [6:0] $end
$var reg 3 . baudCnt [2:0] $end
$var reg 1 / baudTick $end
$var reg 1 0 baudTick8x $end
$var reg 4 1 nextMiddle [3:0] $end
$var reg 1 2 ping $end
$var reg 9 3 rxBuf [8:0] $end
$var reg 4 4 rxCnt [3:0] $end
$var reg 1 5 rxReady $end
$var reg 10 6 txBuf [9:0] $end
$var reg 4 7 txCnt [3:0] $end
$var reg 1 8 txTriggered $end
$upscope $end
$upscope $end
$enddefinitions $end
#50
$dumpvars
08
b0 7
b0 6
05
b0 4
b0 3
02
b0 1
00
0/
b0 .
b11 -
b0 ,
b0 +
b1010101 *
0)
b0 (
0'
1&
0%
0$
1#
1"
1!
$end
#60
0&
#70
b100 -
1&
#80
0&
#90
b101 -
1&
#100
0&
#110
b110 -
1&
#120
0&
#130
b111 -
1&
#140
0&
#150
b1000 -
1&
#160
0&
#170
b1001 -
1&
#180
0&
#190
b1010 -
1&
#200
0&
#210
b1011 -
1&
#220
0&
#230
b1100 -
1&
#240
0&
#250
b1101 -
1&
#260
0&
#270
b1110 -
1&
#280
0&
#290
b1111 -
1&
#300
0&
#310
b10000 -
1&
#320
0&
#330
b10001 -
1&
#340
0&
#350
b10010 -
1&
#360
0&
#370
b10011 -
1&
#380
0&
#390
b10100 -
1&
#400
0&
#410
b10101 -
1&
#420
0&
#430
b10110 -
1&
#440
0&
#450
b10111 -
1&
#460
0&
#470
b11000 -
1&
#480
0&
#490
b11001 -
1&
#500
0&
#510
b11010 -
1&
#520
0&
#530
b11011 -
1&
#540
0&
#550
b11100 -
1&
#560
0&
#570
b11101 -
1&
#580
0&
#590
b11110 -
1&
#600
0&
#610
b11111 -
1&
#620
0&
#630
b100000 -
1&
#640
0&
#650
b100001 -
1&
#660
0&
#670
b100010 -
1&
#680
0&
#690
b100011 -
1&
#700
0&
#710
b100100 -
1&
#720
0&
#730
b100101 -
1&
#740
0&
#750
b100110 -
1&
#760
0&
#770
b100111 -
1&
#780
0&
#790
b101000 -
1&
#800
0&
#810
b101001 -
1&
#820
0&
#830
b101010 -
1&
#840
0&
#850
b101011 -
1&
#860
0&
#870
b101100 -
1&
#880
0&
#890
b101101 -
1&
#900
0&
#910
b101110 -
1&
#920
0&
#930
b101111 -
1&
#940
0&
#950
b110000 -
1&
#960
0&
#970
b110001 -
1&
#980
0&
#990
b110010 -
1&
#1000
0&
#1010
b110011 -
1&
#1020
0&
#1030
b110100 -
1&
#1040
0&
#1050
b110101 -
1&
#1060
0&
#1070
b110110 -
1&
#1080
0&
#1090
b110111 -
1&
#1100
0&
#1110
b111000 -
1&
#1120
0&
#1130
b111001 -
1&
#1140
0&
#1150
b111010 -
1&
#1160
0&
#1170
b111011 -
1&
#1180
0&
#1190
b111100 -
1&
#1200
0&
#1210
b111101 -
1&
#1220
0&
#1230
b111110 -
1&
#1240
0&
#1250
b111111 -
1&
#1260
0&
#1270
b1000000 -
1&
#1280
0&
#1290
b1000001 -
1&
#1300
0&
#1310
b1000010 -
1&
#1320
0&
#1330
b1000011 -
1&
#1340
0&
#1350
b1000100 -
1&
#1360
0&
#1370
b1000101 -
1&
#1380
0&
#1390
b1000110 -
1&
#1400
0&
#1410
b1000111 -
1&
#1420
0&
#1430
b1001000 -
1&
#1440
0&
#1450
b1001001 -
1&
#1460
0&
#1470
b1001010 -
1&
#1480
0&
#1490
b1001011 -
1&
#1500
0&
#1510
b1001100 -
1&
#1520
0&
#1530
b1001101 -
1&
#1540
0&
#1550
b1001110 -
1&
#1560
0&
#1570
b1001111 -
1&
#1580
0&
#1590
b1010000 -
1&
#1600
0&
#1610
b1010001 -
1&
#1620
0&
#1630
b1010010 -
1&
#1640
0&
#1650
b1010011 -
1&
#1660
0&
#1670
b1010100 -
1&
#1680
0&
#1690
b1010101 -
1&
#1700
0&
#1710
b1010110 -
1&
#1720
0&
#1730
b1010111 -
1&
#1740
0&
#1750
b1011000 -
1&
#1760
0&
#1770
b1011001 -
1&
#1780
0&
#1790
b1011010 -
1&
#1800
0&
#1810
b1011011 -
1&
#1820
0&
#1830
b1011100 -
1&
#1840
0&
#1850
b1011101 -
1&
#1860
0&
#1870
b1011110 -
1&
#1880
0&
#1890
b1011111 -
1&
#1900
0&
#1910
b1100000 -
1&
#1920
0&
#1930
b1100001 -
1&
#1940
0&
#1950
b1100010 -
1&
#1960
0&
#1970
b1100011 -
1&
#1980
0&
#1990
b1100100 -
1&
#2000
0&
#2010
b1100101 -
1&
#2020
0&
#2030
b1100110 -
1&
#2040
0&
#2050
b1100111 -
1&
#2060
0&
#2070
b1101000 -
1&
#2080
0&
#2090
b1101001 -
1&
#2100
0&
#2110
b1101010 -
1&
#2120
0&
#2130
b1101011 -
1&
#2140
0&
#2150
10
b0 -
1&
#2160
0&
#2170
1/
b1 .
00
b1 -
1&
#2180
0&
#2190
0/
b10 -
1&
#2200
0&
#2210
b11 -
1&
#2220
0&
#2230
b100 -
1&
#2240
0&
#2250
b101 -
1&
#2260
0&
#2270
b110 -
1&
#2280
0&
#2290
b111 -
1&
#2300
0&
#2310
b1000 -
1&
#2320
0&
#2330
b1001 -
1&
#2340
0&
#2350
b1010 -
1&
#2360
0&
#2370
b1011 -
1&
#2380
0&
#2390
b1100 -
1&
#2400
0&
#2410
b1101 -
1&
#2420
0&
#2430
b1110 -
1&
#2440
0&
#2450
b1111 -
1&
#2460
0&
#2470
b10000 -
1&
#2480
0&
#2490
b10001 -
1&
#2500
0&
#2510
b10010 -
1&
#2520
0&
#2530
b10011 -
1&
#2540
0&
#2550
b10100 -
1&
#2560
0&
#2570
b10101 -
1&
#2580
0&
#2590
b10110 -
1&
#2600
0&
#2610
b10111 -
1&
#2620
0&
#2630
b11000 -
1&
#2640
0&
#2650
b11001 -
1&
#2660
0&
#2670
b11010 -
1&
#2680
0&
#2690
b11011 -
1&
#2700
0&
#2710
b11100 -
1&
#2720
0&
#2730
b11101 -
1&
#2740
0&
#2750
b11110 -
1&
#2760
0&
#2770
b11111 -
1&
#2780
0&
#2790
b100000 -
1&
#2800
0&
#2810
b100001 -
1&
#2820
0&
#2830
b100010 -
1&
#2840
0&
#2850
b100011 -
1&
#2860
0&
#2870
b100100 -
1&
#2880
0&
#2890
b100101 -
1&
#2900
0&
#2910
b100110 -
1&
#2920
0&
#2930
b100111 -
1&
#2940
0&
#2950
b101000 -
1&
#2960
0&
#2970
b101001 -
1&
#2980
0&
#2990
b101010 -
1&
#3000
0&
#3010
b101011 -
1&
#3020
0&
#3030
b101100 -
1&
#3040
0&
#3050
b101101 -
1&
#3060
0&
#3070
b101110 -
1&
#3080
0&
#3090
b101111 -
1&
#3100
0&
#3110
b110000 -
1&
#3120
0&
#3130
b110001 -
1&
#3140
0&
#3150
b110010 -
1&
#3160
0&
#3170
b110011 -
1&
#3180
0&
#3190
b110100 -
1&
#3200
0&
#3210
b110101 -
1&
#3220
0&
#3230
b110110 -
1&
#3240
0&
#3250
b110111 -
1&
#3260
0&
#3270
b111000 -
1&
#3280
0&
#3290
b111001 -
1&
#3300
0&
#3310
b111010 -
1&
#3320
0&
#3330
b111011 -
1&
#3340
0&
#3350
b111100 -
1&
#3360
0&
#3370
b111101 -
1&
#3380
0&
#3390
b111110 -
1&
#3400
0&
#3410
b111111 -
1&
#3420
0&
#3430
b1000000 -
1&
#3440
0&
#3450
b1000001 -
1&
#3460
0&
#3470
b1000010 -
1&
#3480
0&
#3490
b1000011 -
1&
#3500
0&
#3510
b1000100 -
1&
#3520
0&
#3530
b1000101 -
1&
#3540
0&
#3550
b1000110 -
1&
#3560
0&
#3570
b1000111 -
1&
#3580
0&
#3590
b1001000 -
1&
#3600
0&
#3610
b1001001 -
1&
#3620
0&
#3630
b1001010 -
1&
#3640
0&
#3650
b1001011 -
1&
#3660
0&
#3670
b1001100 -
1&
#3680
0&
#3690
b1001101 -
1&
#3700
0&
#3710
b1001110 -
1&
#3720
0&
#3730
b1001111 -
1&
#3740
0&
#3750
b1010000 -
1&
#3760
0&
#3770
b1010001 -
1&
#3780
0&
#3790
b1010010 -
1&
#3800
0&
#3810
b1010011 -
1&
#3820
0&
#3830
b1010100 -
1&
#3840
0&
#3850
b1010101 -
1&
#3860
0&
#3870
b1010110 -
1&
#3880
0&
#3890
b1010111 -
1&
#3900
0&
#3910
b1011000 -
1&
#3920
0&
#3930
b1011001 -
1&
#3940
0&
#3950
b1011010 -
1&
#3960
0&
#3970
b1011011 -
1&
#3980
0&
#3990
b1011100 -
1&
#4000
0&
#4010
b1011101 -
1&
#4020
0&
#4030
b1011110 -
1&
#4040
0&
#4050
b1011111 -
1&
#4060
0&
#4070
b1100000 -
1&
#4080
0&
#4090
b1100001 -
1&
#4100
0&
#4110
b1100010 -
1&
#4120
0&
#4130
b1100011 -
1&
#4140
0&
#4150
b1100100 -
1&
#4160
0&
#4170
b1100101 -
1&
#4180
0&
#4190
b1100110 -
1&
#4200
0&
#4210
b1100111 -
1&
#4220
0&
#4230
b1101000 -
1&
#4240
0&
#4250
b1101001 -
1&
#4260
0&
#4270
b1101010 -
1&
#4280
0&
#4290
b1101011 -
1&
#4300
0&
#4310
10
b0 -
1&
#4320
0&
#4330
b10 .
00
b1 -
1&
#4340
0&
#4350
b10 -
1&
#4360
0&
#4370
b11 -
1&
#4380
0&
#4390
b100 -
1&
#4400
0&
#4410
b101 -
1&
#4420
0&
#4430
b110 -
1&
#4440
0&
#4450
b111 -
1&
#4460
0&
#4470
b1000 -
1&
#4480
0&
#4490
b1001 -
1&
#4500
0&
#4510
b1010 -
1&
#4520
0&
#4530
b1011 -
1&
#4540
0&
#4550
b1100 -
1&
#4560
0&
#4570
b1101 -
1&
#4580
0&
#4590
b1110 -
1&
#4600
0&
#4610
b1111 -
1&
#4620
0&
#4630
b10000 -
1&
#4640
0&
#4650
b10001 -
1&
#4660
0&
#4670
b10010 -
1&
#4680
0&
#4690
b10011 -
1&
#4700
0&
#4710
b10100 -
1&
#4720
0&
#4730
b10101 -
1&
#4740
0&
#4750
b10110 -
1&
#4760
0&
#4770
b10111 -
1&
#4780
0&
#4790
b11000 -
1&
#4800
0&
#4810
b11001 -
1&
#4820
0&
#4830
b11010 -
1&
#4840
0&
#4850
b11011 -
1&
#4860
0&
#4870
b11100 -
1&
#4880
0&
#4890
b11101 -
1&
#4900
0&
#4910
b11110 -
1&
#4920
0&
#4930
b11111 -
1&
#4940
0&
#4950
b100000 -
1&
#4960
0&
#4970
b100001 -
1&
#4980
0&
#4990
b100010 -
1&
#5000
0&
#5010
b100011 -
1&
#5020
0&
#5030
b100100 -
1&
#5040
0&
#5050
b100101 -
1&
#5060
0&
#5070
b100110 -
1&
#5080
0&
#5090
b100111 -
1&
#5100
0&
#5110
b101000 -
1&
#5120
0&
#5130
b101001 -
1&
#5140
0&
#5150
b101010 -
1&
#5160
0&
#5170
b101011 -
1&
#5180
0&
#5190
b101100 -
1&
#5200
0&
#5210
b101101 -
1&
#5220
0&
#5230
b101110 -
1&
#5240
0&
#5250
b101111 -
1&
#5260
0&
#5270
b110000 -
1&
#5280
0&
#5290
b110001 -
1&
#5300
0&
#5310
b110010 -
1&
#5320
0&
#5330
b110011 -
1&
#5340
0&
#5350
b110100 -
1&
#5360
0&
#5370
b110101 -
1&
#5380
0&
#5390
b110110 -
1&
#5400
0&
#5410
b110111 -
1&
#5420
0&
#5430
b111000 -
1&
#5440
0&
#5450
b111001 -
1&
#5460
0&
#5470
b111010 -
1&
#5480
0&
#5490
b111011 -
1&
#5500
0&
#5510
b111100 -
1&
#5520
0&
#5530
b111101 -
1&
#5540
0&
#5550
b111110 -
1&
#5560
0&
#5570
b111111 -
1&
#5580
0&
#5590
b1000000 -
1&
#5600
0&
#5610
b1000001 -
1&
#5620
0&
#5630
b1000010 -
1&
#5640
0&
#5650
b1000011 -
1&
#5660
0&
#5670
b1000100 -
1&
#5680
0&
#5690
b1000101 -
1&
#5700
0&
#5710
b1000110 -
1&
#5720
0&
#5730
b1000111 -
1&
#5740
0&
#5750
b1001000 -
1&
#5760
0&
#5770
b1001001 -
1&
#5780
0&
#5790
b1001010 -
1&
#5800
0&
#5810
b1001011 -
1&
#5820
0&
#5830
b1001100 -
1&
#5840
0&
#5850
b1001101 -
1&
#5860
0&
#5870
b1001110 -
1&
#5880
0&
#5890
b1001111 -
1&
#5900
0&
#5910
b1010000 -
1&
#5920
0&
#5930
b1010001 -
1&
#5940
0&
#5950
b1010010 -
1&
#5960
0&
#5970
b1010011 -
1&
#5980
0&
#5990
b1010100 -
1&
#6000
0&
#6010
b1010101 -
1&
#6020
0&
#6030
b1010110 -
1&
#6040
0&
#6050
b1010111 -
1&
#6060
0&
#6070
b1011000 -
1&
#6080
0&
#6090
b1011001 -
1&
#6100
0&
#6110
b1011010 -
1&
#6120
0&
#6130
b1011011 -
1&
#6140
0&
#6150
b1011100 -
1&
#6160
0&
#6170
b1011101 -
1&
#6180
0&
#6190
b1011110 -
1&
#6200
0&
#6210
b1011111 -
1&
#6220
0&
#6230
b1100000 -
1&
#6240
0&
#6250
b1100001 -
1&
#6260
0&
#6270
b1100010 -
1&
#6280
0&
#6290
b1100011 -
1&
#6300
0&
#6310
b1100100 -
1&
#6320
0&
#6330
b1100101 -
1&
#6340
0&
#6350
b1100110 -
1&
#6360
0&
#6370
b1100111 -
1&
#6380
0&
#6390
b1101000 -
1&
#6400
0&
#6410
b1101001 -
1&
#6420
0&
#6430
b1101010 -
1&
#6440
0&
#6450
b1101011 -
1&
#6460
0&
#6470
10
b0 -
1&
#6480
0&
#6490
b11 .
00
b1 -
1&
#6500
0&
#6510
b10 -
1&
#6520
0&
#6530
b11 -
1&
#6540
0&
#6550
b100 -
1&
#6560
0&
#6570
b101 -
1&
#6580
0&
#6590
b110 -
1&
#6600
0&
#6610
b111 -
1&
#6620
0&
#6630
b1000 -
1&
#6640
0&
#6650
b1001 -
1&
#6660
0&
#6670
b1010 -
1&
#6680
0&
#6690
b1011 -
1&
#6700
0&
#6710
b1100 -
1&
#6720
0&
#6730
b1101 -
1&
#6740
0&
#6750
b1110 -
1&
#6760
0&
#6770
b1111 -
1&
#6780
0&
#6790
b10000 -
1&
#6800
0&
#6810
b10001 -
1&
#6820
0&
#6830
b10010 -
1&
#6840
0&
#6850
b10011 -
1&
#6860
0&
#6870
b10100 -
1&
#6880
0&
#6890
b10101 -
1&
#6900
0&
#6910
b10110 -
1&
#6920
0&
#6930
b10111 -
1&
#6940
0&
#6950
b11000 -
1&
#6960
0&
#6970
b11001 -
1&
#6980
0&
#6990
b11010 -
1&
#7000
0&
#7010
b11011 -
1&
#7020
0&
#7030
b11100 -
1&
#7040
0&
#7050
b11101 -
1&
#7060
0&
#7070
b11110 -
1&
#7080
0&
#7090
b11111 -
1&
#7100
0&
#7110
b100000 -
1&
#7120
0&
#7130
b100001 -
1&
#7140
0&
#7150
b100010 -
1&
#7160
0&
#7170
b100011 -
1&
#7180
0&
#7190
b100100 -
1&
#7200
0&
#7210
b100101 -
1&
#7220
0&
#7230
b100110 -
1&
#7240
0&
#7250
b100111 -
1&
#7260
0&
#7270
b101000 -
1&
#7280
0&
#7290
b101001 -
1&
#7300
0&
#7310
b101010 -
1&
#7320
0&
#7330
b101011 -
1&
#7340
0&
#7350
b101100 -
1&
#7360
0&
#7370
b101101 -
1&
#7380
0&
#7390
b101110 -
1&
#7400
0&
#7410
b101111 -
1&
#7420
0&
#7430
b110000 -
1&
#7440
0&
#7450
b110001 -
1&
#7460
0&
#7470
b110010 -
1&
#7480
0&
#7490
b110011 -
1&
#7500
0&
#7510
b110100 -
1&
#7520
0&
#7530
b110101 -
1&
#7540
0&
#7550
b110110 -
1&
#7560
0&
#7570
b110111 -
1&
#7580
0&
#7590
b111000 -
1&
#7600
0&
#7610
b111001 -
1&
#7620
0&
#7630
b111010 -
1&
#7640
0&
#7650
b111011 -
1&
#7660
0&
#7670
b111100 -
1&
#7680
0&
#7690
b111101 -
1&
#7700
0&
#7710
b111110 -
1&
#7720
0&
#7730
b111111 -
1&
#7740
0&
#7750
b1000000 -
1&
#7760
0&
#7770
b1000001 -
1&
#7780
0&
#7790
b1000010 -
1&
#7800
0&
#7810
b1000011 -
1&
#7820
0&
#7830
b1000100 -
1&
#7840
0&
#7850
b1000101 -
1&
#7860
0&
#7870
b1000110 -
1&
#7880
0&
#7890
b1000111 -
1&
#7900
0&
#7910
b1001000 -
1&
#7920
0&
#7930
b1001001 -
1&
#7940
0&
#7950
b1001010 -
1&
#7960
0&
#7970
b1001011 -
1&
#7980
0&
#7990
b1001100 -
1&
#8000
0&
#8010
b1001101 -
1&
#8020
0&
#8030
b1001110 -
1&
#8040
0&
#8050
b1001111 -
1&
#8060
0&
#8070
b1010000 -
1&
#8080
0&
#8090
b1010001 -
1&
#8100
0&
#8110
b1010010 -
1&
#8120
0&
#8130
b1010011 -
1&
#8140
0&
#8150
b1010100 -
1&
#8160
0&
#8170
b1010101 -
1&
#8180
0&
#8190
b1010110 -
1&
#8200
0&
#8210
b1010111 -
1&
#8220
0&
#8230
b1011000 -
1&
#8240
0&
#8250
b1011001 -
1&
#8260
0&
#8270
b1011010 -
1&
#8280
0&
#8290
b1011011 -
1&
#8300
0&
#8310
b1011100 -
1&
#8320
0&
#8330
b1011101 -
1&
#8340
0&
#8350
b1011110 -
1&
#8360
0&
#8370
b1011111 -
1&
#8380
0&
#8390
b1100000 -
1&
#8400
0&
#8410
b1100001 -
1&
#8420
0&
#8430
b1100010 -
1&
#8440
0&
#8450
b1100011 -
1&
#8460
0&
#8470
b1100100 -
1&
#8480
0&
#8490
b1100101 -
1&
#8500
0&
#8510
b1100110 -
1&
#8520
0&
#8530
b1100111 -
1&
#8540
0&
#8550
b1101000 -
1&
#8560
0&
#8570
b1101001 -
1&
#8580
0&
#8590
b1101010 -
1&
#8600
0&
#8610
b1101011 -
1&
#8620
0&
#8630
10
b0 -
1&
#8640
0&
#8650
b100 .
00
b1 -
1&
#8660
0&
#8670
b10 -
1&
#8680
0&
#8690
b11 -
1&
#8700
0&
#8710
b100 -
1&
#8720
0&
#8730
b101 -
1&
#8740
0&
#8750
b110 -
1&
#8760
0&
#8770
b111 -
1&
#8780
0&
#8790
b1000 -
1&
#8800
0&
#8810
b1001 -
1&
#8820
0&
#8830
b1010 -
1&
#8840
0&
#8850
b1011 -
1&
#8860
0&
#8870
b1100 -
1&
#8880
0&
#8890
b1101 -
1&
#8900
0&
#8910
b1110 -
1&
#8920
0&
#8930
b1111 -
1&
#8940
0&
#8950
b10000 -
1&
#8960
0&
#8970
b10001 -
1&
#8980
0&
#8990
b10010 -
1&
#9000
0&
#9010
b10011 -
1&
#9020
0&
#9030
b10100 -
1&
#9040
0&
#9050
b10101 -
1&
#9060
0&
#9070
b10110 -
1&
#9080
0&
#9090
b10111 -
1&
#9100
0&
#9110
b11000 -
1&
#9120
0&
#9130
b11001 -
1&
#9140
0&
#9150
b11010 -
1&
#9160
0&
#9170
b11011 -
1&
#9180
0&
#9190
b11100 -
1&
#9200
0&
#9210
b11101 -
1&
#9220
0&
#9230
b11110 -
1&
#9240
0&
#9250
b11111 -
1&
#9260
0&
#9270
b100000 -
1&
#9280
0&
#9290
b100001 -
1&
#9300
0&
#9310
b100010 -
1&
#9320
0&
#9330
b100011 -
1&
#9340
0&
#9350
b100100 -
1&
#9360
0&
#9370
b100101 -
1&
#9380
0&
#9390
b100110 -
1&
#9400
0&
#9410
b100111 -
1&
#9420
0&
#9430
b101000 -
1&
#9440
0&
#9450
b101001 -
1&
#9460
0&
#9470
b101010 -
1&
#9480
0&
#9490
b101011 -
1&
#9500
0&
#9510
b101100 -
1&
#9520
0&
#9530
b101101 -
1&
#9540
0&
#9550
b101110 -
1&
#9560
0&
#9570
b101111 -
1&
#9580
0&
#9590
b110000 -
1&
#9600
0&
#9610
b110001 -
1&
#9620
0&
#9630
b110010 -
1&
#9640
0&
#9650
b110011 -
1&
#9660
0&
#9670
b110100 -
1&
#9680
0&
#9690
b110101 -
1&
#9700
0&
#9710
b110110 -
1&
#9720
0&
#9730
b110111 -
1&
#9740
0&
#9750
b111000 -
1&
#9760
0&
#9770
b111001 -
1&
#9780
0&
#9790
b111010 -
1&
#9800
0&
#9810
b111011 -
1&
#9820
0&
#9830
b111100 -
1&
#9840
0&
#9850
b111101 -
1&
#9860
0&
#9870
b111110 -
1&
#9880
0&
#9890
b111111 -
1&
#9900
0&
#9910
b1000000 -
1&
#9920
0&
#9930
b1000001 -
1&
#9940
0&
#9950
b1000010 -
1&
#9960
0&
#9970
b1000011 -
1&
#9980
0&
#9990
b1000100 -
1&
#10000
0&
#10010
b1000101 -
1&
#10020
0&
#10030
b1000110 -
1&
